pycantus/__init__.py
pycantus/data.py
pycantus/load_data_old.py
pycantus/preprocessor.py
pycantus/analytics/__init__.py
pycantus/dataloaders/__init__.py
pycantus/dataloaders/loader.py
pycantus/dataloaders/parsers.py
pycantus/dataset_files/sample_dataset/chants.csv
pycantus/dataset_files/sample_dataset/sources.csv
pycantus/models/__init__.py
pycantus/models/chant.py
pycantus/models/corpus.py
pycantus/models/melody.py
pycantus/models/source.py
pycantus/static/available_datasets.json
pycantus/static/genre.csv
pycantus/volpiano/__init__.py
pycantus/volpiano/utils.py
pycantus-0.0.3.dist-info/METADATA
pycantus-0.0.3.dist-info/WHEEL
pycantus-0.0.3.dist-info/licenses/LICENSE
pycantus-0.0.3.dist-info/RECORD
