Metadata-Version: 2.4
Name: pycantus
Version: 0.0.3
Summary: PyCantus: A Python library designed to enhance accessibility of Gregorian chants for both coders and non-coders.
Project-URL: Homepage, https://github.com/dact-chant/PyCantus
Project-URL: Documentation, https://github.com/dact-chant/PyCantus/tree/main/docs
Project-URL: Repository, https://github.com/dact-chant/PyCantus.git
Author-email: Anna Dvorakova <anna.dvorakova332@student.cuni.cz>, Tim Eipert <tim.eipert@uni-wuerzburg.de>, "Jan Hajic jr." <hajicj@ufal.mff.cuni.cz>, Vojtech Lanz <lanz@ufal.mff.cuni.cz>
Maintainer-email: Tim Eipert <tim.eipert@uni-wuerzburg.de>, "Jan Hajic jr." <hajicj@ufal.mff.cuni.cz>, Vojtech Lanz <lanz@ufal.mff.cuni.cz>, Anna Dvorakova <anna.dvorakova332@student.cuni.cz>
License: Copyright (c) 2022-2024 Jan Hajic and others
License-File: LICENSE
Keywords: Cantus,Gregorian Chant
Classifier: Development Status :: 2 - Pre-Alpha
Classifier: Intended Audience :: Science/Research
Classifier: License :: OSI Approved :: MIT License
Classifier: Programming Language :: Python
Classifier: Topic :: Scientific/Engineering :: Information Analysis
Requires-Python: >=3.10
Requires-Dist: pandas==2.2.2
Requires-Dist: requests==2.31.0
Provides-Extra: examples
Provides-Extra: tests
